[
    {
        "nimi": "Tallinn",
        "temp": -2,
        "tuul": 5.0,
        "ikoon": "⛅",
        "min": -6,
        "max": -1,
        "sadu": 0.0
    },
    {
        "nimi": "Tartu",
        "temp": -1,
        "tuul": 5.4,
        "ikoon": "☀️",
        "min": -8,
        "max": 0,
        "sadu": 0.0
    },
    {
        "nimi": "Pärnu",
        "temp": -2,
        "tuul": 5.0,
        "ikoon": "☀️",
        "min": -9,
        "max": 0,
        "sadu": 0.0
    },
    {
        "nimi": "Kuressaare",
        "temp": -1,
        "tuul": 6.8,
        "ikoon": "☀️",
        "min": -8,
        "max": -1,
        "sadu": 0.0
    },
    {
        "nimi": "Viljandi",
        "temp": -2,
        "tuul": 6.1,
        "ikoon": "☀️",
        "min": -8,
        "max": -1,
        "sadu": 0.1
    }
]