[
    {
        "nimi": "Tallinn",
        "temp": 3,
        "tuul": 15.1,
        "ikoon": "⛅",
        "min": 2,
        "max": 4,
        "sadu": 2.5
    },
    {
        "nimi": "Tartu",
        "temp": 4,
        "tuul": 10.1,
        "ikoon": "⛅",
        "min": 2,
        "max": 5,
        "sadu": 5.2
    },
    {
        "nimi": "Pärnu",
        "temp": 2,
        "tuul": 18.4,
        "ikoon": "⛅",
        "min": 1,
        "max": 3,
        "sadu": 3.8
    },
    {
        "nimi": "Kuressaare",
        "temp": 2,
        "tuul": 9.7,
        "ikoon": "⛅",
        "min": 0,
        "max": 3,
        "sadu": 1.2
    },
    {
        "nimi": "Viljandi",
        "temp": 2,
        "tuul": 11.5,
        "ikoon": "⛅",
        "min": 1,
        "max": 3,
        "sadu": 4.5
    }
]