[
    {
        "nimi": "Tallinn",
        "temp": 18,
        "tuul": 5.0,
        "ikoon": "⛅",
        "min": 18,
        "max": 24,
        "sadu": 0.0
    },
    {
        "nimi": "Tartu",
        "temp": 18,
        "tuul": 5.4,
        "ikoon": "⛅",
        "min": 18,
        "max": 26,
        "sadu": 0.0
    },
    {
        "nimi": "Pärnu",
        "temp": 16,
        "tuul": 6.1,
        "ikoon": "☀️",
        "min": 16,
        "max": 24,
        "sadu": 0.0
    },
    {
        "nimi": "Kuressaare",
        "temp": 13,
        "tuul": 5.0,
        "ikoon": "☀️",
        "min": 12,
        "max": 22,
        "sadu": 0.0
    },
    {
        "nimi": "Viljandi",
        "temp": 15,
        "tuul": 5.8,
        "ikoon": "☀️",
        "min": 15,
        "max": 24,
        "sadu": 0.0
    }
]